GitOps_Repo_Orchestrator/__init__.py
GitOps_Repo_Orchestrator/cli.py
GitOps_Repo_Orchestrator/config.py
GitOps_Repo_Orchestrator/commands/edit.py
GitOps_Repo_Orchestrator/commands/status.py
GitOps_Repo_Orchestrator/commands/sync.py
GitOps_Repo_Orchestrator/tui/__init__.py
GitOps_Repo_Orchestrator/tui/app.py
GitOps_Repo_Orchestrator/tui/utils.py
GitOps_Repo_Orchestrator/tui/css/dialogs.tcss
GitOps_Repo_Orchestrator/tui/css/global.css
GitOps_Repo_Orchestrator/tui/dialogs/__init__.py
GitOps_Repo_Orchestrator/tui/dialogs/confirm_dialog.py
GitOps_Repo_Orchestrator/tui/dialogs/repo_dialog.py
GitOps_Repo_Orchestrator/tui/dialogs/status_dialog.py
GitOps_Repo_Orchestrator/tui/dialogs/sync_dialog.py
GitOps_Repo_Orchestrator/tui/widgets/__init__.py
GitOps_Repo_Orchestrator/tui/widgets/repo_details.py
GitOps_Repo_Orchestrator/tui/widgets/repo_list.py
GitOps_Repo_Orchestrator/tui/widgets/status_bar.py
gitops_repo_orchestrator-0.5.0.dist-info/METADATA
gitops_repo_orchestrator-0.5.0.dist-info/WHEEL
gitops_repo_orchestrator-0.5.0.dist-info/entry_points.txt
gitops_repo_orchestrator-0.5.0.dist-info/RECORD
